{
  "audit_time_utc": "2026-06-18T15:53:08.221461+00:00",
  "db_path": "/Users/liudapeng/Documents/code/others/world_cup/backend/world_cup.db",
  "latest_model_score_id": 486,
  "latest_revision_id": 599,
  "total_finished": 24,
  "has_match_prediction": 22,
  "has_pre_kickoff_snapshot": 8,
  "actually_scored": 8,
  "missing_snapshot": 16,
  "post_kickoff_snapshot_count": 0,
  "match_details": [
    {
      "match_id": "2026-A-MEX-RSA-2026-06-11",
      "home_team": "Mexico",
      "away_team": "South Africa",
      "kickoff": "2026-06-11T19:00:00+00:00",
      "status": "final",
      "home_score": 2,
      "away_score": 0,
      "match_predictions_count": 0,
      "pre_kickoff_snapshots_count": 0,
      "post_kickoff_snapshots_count": 0,
      "latest_legal_snapshot_at": null,
      "scorable": false,
      "unscorable_reason": "no_snapshot_at_all"
    },
    {
      "match_id": "2026-A-KOR-CZE-2026-06-11",
      "home_team": "South Korea",
      "away_team": "Czech Republic",
      "kickoff": "2026-06-12T02:00:00+00:00",
      "status": "final",
      "home_score": 2,
      "away_score": 1,
      "match_predictions_count": 0,
      "pre_kickoff_snapshots_count": 0,
      "post_kickoff_snapshots_count": 0,
      "latest_legal_snapshot_at": null,
      "scorable": false,
      "unscorable_reason": "no_snapshot_at_all"
    },
    {
      "match_id": "2026-B-CAN-BIH-2026-06-12",
      "home_team": "Canada",
      "away_team": "Bosnia & Herzegovina",
      "kickoff": "2026-06-12T19:00:00+00:00",
      "status": "final",
      "home_score": 1,
      "away_score": 1,
      "match_predictions_count": 5,
      "pre_kickoff_snapshots_count": 0,
      "post_kickoff_snapshots_count": 0,
      "latest_legal_snapshot_at": null,
      "scorable": false,
      "unscorable_reason": "no_snapshot_at_all"
    },
    {
      "match_id": "2026-D-USA-PAR-2026-06-12",
      "home_team": "USA",
      "away_team": "Paraguay",
      "kickoff": "2026-06-13T01:00:00+00:00",
      "status": "final",
      "home_score": 4,
      "away_score": 1,
      "match_predictions_count": 5,
      "pre_kickoff_snapshots_count": 0,
      "post_kickoff_snapshots_count": 0,
      "latest_legal_snapshot_at": null,
      "scorable": false,
      "unscorable_reason": "no_snapshot_at_all"
    },
    {
      "match_id": "2026-B-QAT-SUI-2026-06-13",
      "home_team": "Qatar",
      "away_team": "Switzerland",
      "kickoff": "2026-06-13T19:00:00+00:00",
      "status": "final",
      "home_score": 1,
      "away_score": 1,
      "match_predictions_count": 5,
      "pre_kickoff_snapshots_count": 0,
      "post_kickoff_snapshots_count": 0,
      "latest_legal_snapshot_at": null,
      "scorable": false,
      "unscorable_reason": "no_snapshot_at_all"
    },
    {
      "match_id": "2026-C-BRA-MAR-2026-06-13",
      "home_team": "Brazil",
      "away_team": "Morocco",
      "kickoff": "2026-06-13T22:00:00+00:00",
      "status": "final",
      "home_score": 1,
      "away_score": 1,
      "match_predictions_count": 5,
      "pre_kickoff_snapshots_count": 0,
      "post_kickoff_snapshots_count": 0,
      "latest_legal_snapshot_at": null,
      "scorable": false,
      "unscorable_reason": "no_snapshot_at_all"
    },
    {
      "match_id": "2026-C-HAI-SCO-2026-06-13",
      "home_team": "Haiti",
      "away_team": "Scotland",
      "kickoff": "2026-06-14T01:00:00+00:00",
      "status": "final",
      "home_score": 0,
      "away_score": 1,
      "match_predictions_count": 5,
      "pre_kickoff_snapshots_count": 0,
      "post_kickoff_snapshots_count": 0,
      "latest_legal_snapshot_at": null,
      "scorable": false,
      "unscorable_reason": "no_snapshot_at_all"
    },
    {
      "match_id": "2026-D-AUS-TUR-2026-06-13",
      "home_team": "Australia",
      "away_team": "Turkey",
      "kickoff": "2026-06-14T04:00:00+00:00",
      "status": "final",
      "home_score": 2,
      "away_score": 0,
      "match_predictions_count": 5,
      "pre_kickoff_snapshots_count": 0,
      "post_kickoff_snapshots_count": 0,
      "latest_legal_snapshot_at": null,
      "scorable": false,
      "unscorable_reason": "no_snapshot_at_all"
    },
    {
      "match_id": "2026-E-GER-CUW-2026-06-14",
      "home_team": "Germany",
      "away_team": "Curaçao",
      "kickoff": "2026-06-14T17:00:00+00:00",
      "status": "final",
      "home_score": 7,
      "away_score": 1,
      "match_predictions_count": 5,
      "pre_kickoff_snapshots_count": 0,
      "post_kickoff_snapshots_count": 0,
      "latest_legal_snapshot_at": null,
      "scorable": false,
      "unscorable_reason": "no_snapshot_at_all"
    },
    {
      "match_id": "2026-F-NED-JPN-2026-06-14",
      "home_team": "Netherlands",
      "away_team": "Japan",
      "kickoff": "2026-06-14T20:00:00+00:00",
      "status": "final",
      "home_score": 2,
      "away_score": 2,
      "match_predictions_count": 5,
      "pre_kickoff_snapshots_count": 0,
      "post_kickoff_snapshots_count": 0,
      "latest_legal_snapshot_at": null,
      "scorable": false,
      "unscorable_reason": "no_snapshot_at_all"
    },
    {
      "match_id": "2026-E-CIV-ECU-2026-06-14",
      "home_team": "Ivory Coast",
      "away_team": "Ecuador",
      "kickoff": "2026-06-14T23:00:00+00:00",
      "status": "final",
      "home_score": 1,
      "away_score": 0,
      "match_predictions_count": 5,
      "pre_kickoff_snapshots_count": 0,
      "post_kickoff_snapshots_count": 0,
      "latest_legal_snapshot_at": null,
      "scorable": false,
      "unscorable_reason": "no_snapshot_at_all"
    },
    {
      "match_id": "2026-F-SWE-TUN-2026-06-14",
      "home_team": "Sweden",
      "away_team": "Tunisia",
      "kickoff": "2026-06-15T02:00:00+00:00",
      "status": "final",
      "home_score": 5,
      "away_score": 1,
      "match_predictions_count": 5,
      "pre_kickoff_snapshots_count": 0,
      "post_kickoff_snapshots_count": 0,
      "latest_legal_snapshot_at": null,
      "scorable": false,
      "unscorable_reason": "no_snapshot_at_all"
    },
    {
      "match_id": "2026-H-ESP-CPV-2026-06-15",
      "home_team": "Spain",
      "away_team": "Cape Verde",
      "kickoff": "2026-06-15T16:00:00+00:00",
      "status": "final",
      "home_score": 0,
      "away_score": 0,
      "match_predictions_count": 5,
      "pre_kickoff_snapshots_count": 0,
      "post_kickoff_snapshots_count": 0,
      "latest_legal_snapshot_at": null,
      "scorable": false,
      "unscorable_reason": "no_snapshot_at_all"
    },
    {
      "match_id": "2026-G-BEL-EGY-2026-06-15",
      "home_team": "Belgium",
      "away_team": "Egypt",
      "kickoff": "2026-06-15T19:00:00+00:00",
      "status": "final",
      "home_score": 1,
      "away_score": 1,
      "match_predictions_count": 5,
      "pre_kickoff_snapshots_count": 0,
      "post_kickoff_snapshots_count": 0,
      "latest_legal_snapshot_at": null,
      "scorable": false,
      "unscorable_reason": "no_snapshot_at_all"
    },
    {
      "match_id": "2026-H-KSA-URU-2026-06-15",
      "home_team": "Saudi Arabia",
      "away_team": "Uruguay",
      "kickoff": "2026-06-15T22:00:00+00:00",
      "status": "final",
      "home_score": 1,
      "away_score": 1,
      "match_predictions_count": 5,
      "pre_kickoff_snapshots_count": 0,
      "post_kickoff_snapshots_count": 0,
      "latest_legal_snapshot_at": null,
      "scorable": false,
      "unscorable_reason": "no_snapshot_at_all"
    },
    {
      "match_id": "2026-G-IRN-NZL-2026-06-15",
      "home_team": "Iran",
      "away_team": "New Zealand",
      "kickoff": "2026-06-16T01:00:00+00:00",
      "status": "final",
      "home_score": 2,
      "away_score": 2,
      "match_predictions_count": 5,
      "pre_kickoff_snapshots_count": 0,
      "post_kickoff_snapshots_count": 0,
      "latest_legal_snapshot_at": null,
      "scorable": false,
      "unscorable_reason": "no_snapshot_at_all"
    },
    {
      "match_id": "2026-I-FRA-SEN-2026-06-16",
      "home_team": "France",
      "away_team": "Senegal",
      "kickoff": "2026-06-16T19:00:00+00:00",
      "status": "final",
      "home_score": 3,
      "away_score": 1,
      "match_predictions_count": 520,
      "pre_kickoff_snapshots_count": 5,
      "post_kickoff_snapshots_count": 0,
      "latest_legal_snapshot_at": "2026-06-16T18:54:07.074665+00:00",
      "scorable": true,
      "unscorable_reason": null
    },
    {
      "match_id": "2026-I-IRQ-NOR-2026-06-16",
      "home_team": "Iraq",
      "away_team": "Norway",
      "kickoff": "2026-06-16T22:00:00+00:00",
      "status": "final",
      "home_score": 1,
      "away_score": 4,
      "match_predictions_count": 825,
      "pre_kickoff_snapshots_count": 5,
      "post_kickoff_snapshots_count": 0,
      "latest_legal_snapshot_at": "2026-06-16T21:55:15.332610+00:00",
      "scorable": true,
      "unscorable_reason": null
    },
    {
      "match_id": "2026-J-ARG-ALG-2026-06-16",
      "home_team": "Argentina",
      "away_team": "Algeria",
      "kickoff": "2026-06-17T01:00:00+00:00",
      "status": "final",
      "home_score": 3,
      "away_score": 0,
      "match_predictions_count": 1140,
      "pre_kickoff_snapshots_count": 5,
      "post_kickoff_snapshots_count": 0,
      "latest_legal_snapshot_at": "2026-06-17T00:51:08.973842+00:00",
      "scorable": true,
      "unscorable_reason": null
    },
    {
      "match_id": "2026-J-AUT-JOR-2026-06-16",
      "home_team": "Austria",
      "away_team": "Jordan",
      "kickoff": "2026-06-17T04:00:00+00:00",
      "status": "final",
      "home_score": 3,
      "away_score": 1,
      "match_predictions_count": 1490,
      "pre_kickoff_snapshots_count": 5,
      "post_kickoff_snapshots_count": 0,
      "latest_legal_snapshot_at": "2026-06-17T03:50:48.549530+00:00",
      "scorable": true,
      "unscorable_reason": null
    },
    {
      "match_id": "2026-K-POR-COD-2026-06-17",
      "home_team": "Portugal",
      "away_team": "DR Congo",
      "kickoff": "2026-06-17T17:00:00+00:00",
      "status": "final",
      "home_score": 1,
      "away_score": 1,
      "match_predictions_count": 1920,
      "pre_kickoff_snapshots_count": 180,
      "post_kickoff_snapshots_count": 0,
      "latest_legal_snapshot_at": "2026-06-17T16:59:48.663091+00:00",
      "scorable": true,
      "unscorable_reason": null
    },
    {
      "match_id": "2026-L-ENG-CRO-2026-06-17",
      "home_team": "England",
      "away_team": "Croatia",
      "kickoff": "2026-06-17T20:00:00+00:00",
      "status": "final",
      "home_score": 4,
      "away_score": 2,
      "match_predictions_count": 2225,
      "pre_kickoff_snapshots_count": 350,
      "post_kickoff_snapshots_count": 0,
      "latest_legal_snapshot_at": "2026-06-17T19:53:30.118067+00:00",
      "scorable": true,
      "unscorable_reason": null
    },
    {
      "match_id": "2026-L-GHA-PAN-2026-06-17",
      "home_team": "Ghana",
      "away_team": "Panama",
      "kickoff": "2026-06-17T23:00:00+00:00",
      "status": "final",
      "home_score": 1,
      "away_score": 0,
      "match_predictions_count": 2555,
      "pre_kickoff_snapshots_count": 665,
      "post_kickoff_snapshots_count": 0,
      "latest_legal_snapshot_at": "2026-06-17T22:49:20.182704+00:00",
      "scorable": true,
      "unscorable_reason": null
    },
    {
      "match_id": "2026-K-UZB-COL-2026-06-17",
      "home_team": "Uzbekistan",
      "away_team": "Colombia",
      "kickoff": "2026-06-18T02:00:00+00:00",
      "status": "final",
      "home_score": 1,
      "away_score": 3,
      "match_predictions_count": 2880,
      "pre_kickoff_snapshots_count": 985,
      "post_kickoff_snapshots_count": 0,
      "latest_legal_snapshot_at": "2026-06-18T01:54:59.966442+00:00",
      "scorable": true,
      "unscorable_reason": null
    }
  ],
  "model_scores_distribution": [
    {
      "matches_scored": 1,
      "count": 61,
      "earliest_id": 1,
      "latest_id": 61,
      "earliest_at": "2026-06-16T21:09:57.782521",
      "latest_at": "2026-06-17T00:03:28.032319"
    },
    {
      "matches_scored": 2,
      "count": 63,
      "earliest_id": 62,
      "latest_id": 124,
      "earliest_at": "2026-06-17T00:05:27.059983",
      "latest_at": "2026-06-17T03:02:36.037983"
    },
    {
      "matches_scored": 3,
      "count": 70,
      "earliest_id": 125,
      "latest_id": 194,
      "earliest_at": "2026-06-17T03:05:09.085905",
      "latest_at": "2026-06-17T06:12:28.247388"
    },
    {
      "matches_scored": 4,
      "count": 85,
      "earliest_id": 195,
      "latest_id": 279,
      "earliest_at": "2026-06-17T06:14:31.273798",
      "latest_at": "2026-06-17T19:05:58.354594"
    },
    {
      "matches_scored": 5,
      "count": 61,
      "earliest_id": 280,
      "latest_id": 340,
      "earliest_at": "2026-06-17T19:08:08.622332",
      "latest_at": "2026-06-17T22:01:17.655364"
    },
    {
      "matches_scored": 6,
      "count": 66,
      "earliest_id": 341,
      "latest_id": 406,
      "earliest_at": "2026-06-17T22:03:49.439525",
      "latest_at": "2026-06-18T01:07:13.399402"
    },
    {
      "matches_scored": 7,
      "count": 65,
      "earliest_id": 407,
      "latest_id": 471,
      "earliest_at": "2026-06-18T01:09:20.670673",
      "latest_at": "2026-06-18T04:08:49.138294"
    },
    {
      "matches_scored": 8,
      "count": 15,
      "earliest_id": 472,
      "latest_id": 486,
      "earliest_at": "2026-06-18T04:11:01.509824",
      "latest_at": "2026-06-18T15:39:22.591340"
    }
  ],
  "consistency_check": {
    "api_model_score_matches_scored": 8,
    "db_actually_scored": 8,
    "scorable_snapshot_rows_count": 8,
    "scorable_match_ids": [
      "2026-I-FRA-SEN-2026-06-16",
      "2026-I-IRQ-NOR-2026-06-16",
      "2026-J-ARG-ALG-2026-06-16",
      "2026-J-AUT-JOR-2026-06-16",
      "2026-K-POR-COD-2026-06-17",
      "2026-K-UZB-COL-2026-06-17",
      "2026-L-ENG-CRO-2026-06-17",
      "2026-L-GHA-PAN-2026-06-17"
    ],
    "api_vs_db_consistent": true,
    "scorable_rows_vs_db_consistent": true,
    "breakdown_actually_scored": 8,
    "breakdown_total_finished": 24,
    "breakdown_missing_snapshot": 16,
    "breakdown_vs_db_consistent": true,
    "triple_consistent": true
  },
  "disclaimer": "这是截至 2026-06-18T15:53:08.221461+00:00 的快照，不代表永久固定值。系统持续运行时数据可能变化。"
}